{
    "fluentMethods": true,
    "relationships": [
        {
            "relationshipType": "many-to-one",
            "relationshipValidateRules": "required",
            "relationshipName": "customer",
            "otherEntityName": "customer",
            "otherEntityField": "name"
        }
    ],
    "fields": [
        {
            "fieldName": "code",
            "fieldType": "String",
            "fieldValidateRules": [
                "maxlength"
            ],
            "fieldValidateRulesMaxlength": 40
        },
        {
            "fieldName": "name",
            "fieldType": "String",
            "fieldValidateRules": [
                "maxlength"
            ],
            "fieldValidateRulesMaxlength": 40
        },
        {
            "fieldName": "credit",
            "fieldType": "BigDecimal",
            "fieldValidateRules": [
                "min"
            ],
            "fieldValidateRulesMin": 0
        },
        {
            "fieldName": "isEnabled",
            "fieldType": "Boolean"
        },
        {
            "fieldName": "version",
            "fieldType": "Integer"
        },
        {
            "fieldName": "dr",
            "fieldType": "Integer"
        },
        {
            "fieldName": "ts",
            "fieldType": "ZonedDateTime"
        },
        {
            "fieldName": "creator",
            "fieldType": "String",
            "fieldValidateRules": [
                "maxlength"
            ],
            "fieldValidateRulesMaxlength": 40
        },
        {
            "fieldName": "timeCreated",
            "fieldType": "ZonedDateTime"
        },
        {
            "fieldName": "modifier",
            "fieldType": "String",
            "fieldValidateRules": [
                "maxlength"
            ],
            "fieldValidateRulesMaxlength": 40
        },
        {
            "fieldName": "timeModified",
            "fieldType": "ZonedDateTime"
        }
    ],
    "changelogDate": "20171231093931",
    "entityTableName": "cus_customer_account",
    "dto": "mapstruct",
    "pagination": "pagination",
    "service": "serviceClass",
    "jpaMetamodelFiltering": false,
    "microserviceName": "occMsCustomer"
}